microhhpy/__init__.py
microhhpy/constants.py
microhhpy/logger.py
microhhpy/utils.py
microhhpy/chem/__init__.py
microhhpy/chem/emission_input.py
microhhpy/chem/rfmip_background.py
microhhpy/chem/tuv.py
microhhpy/data/__init__.py
microhhpy/data/microhh_tuv.base
microhhpy/data/rfmip_species.nc
microhhpy/data/van_genuchten_parameters.nc
microhhpy/interp/__init__.py
microhhpy/interp/extrapolate.py
microhhpy/interp/interp_kernels.py
microhhpy/interp/interp_latlon.py
microhhpy/io/__init__.py
microhhpy/io/case_input.py
microhhpy/io/ini_io.py
microhhpy/io/netcdf_io.py
microhhpy/io/read_out.py
microhhpy/land/__init__.py
microhhpy/land/corine_landuse.py
microhhpy/land/hihydrosoil.py
microhhpy/land/ifs_vegetation.py
microhhpy/land/land_surface_input.py
microhhpy/land/lcc_landuse.py
microhhpy/land/lsm_input.py
microhhpy/rad/__init__.py
microhhpy/rad/zenith_angle.py
microhhpy/real/__init__.py
microhhpy/real/global_help_functions.py
microhhpy/real/input_from_regular_latlon.py
microhhpy/real/large_scale.py
microhhpy/real/lbc_help_functions.py
microhhpy/real/nest_les_in_les.py
microhhpy/real/numba_kernels.py
microhhpy/real/sea_input.py
microhhpy/solvers/__init__.py
microhhpy/solvers/pressure_solver_dct.py
microhhpy/spatial/__init__.py
microhhpy/spatial/domain.py
microhhpy/spatial/projection.py
microhhpy/spatial/vertical_grid.py
microhhpy/thermo/__init__.py
microhhpy/thermo/base_state.py
microhhpy/thermo/base_thermo.py
microhhpy-0.1.9.dist-info/LICENSE
microhhpy-0.1.9.dist-info/METADATA
microhhpy-0.1.9.dist-info/WHEEL
microhhpy-0.1.9.dist-info/top_level.txt
microhhpy-0.1.9.dist-info/RECORD
