Metadata-Version: 2.1
Name: microhhpy
Version: 0.1.9
Summary: Python package with utility functions for working with MicroHH LES/DNS.
Author-email: Bart van Stratum <bart@cloudysky.cc>
License: GNU GENERAL PUBLIC LICENSE
Project-URL: Homepage, https://github.com/microhh/microhhpy
Keywords: large eddy simulation,LES,direct numerical simulation,DNS,computational fluid dynamics,CFD,meteorology,turbulence
Classifier: License :: OSI Approved :: GNU General Public License v3 (GPLv3)
Classifier: Programming Language :: Python
Classifier: Programming Language :: Python :: 3
Classifier: Operating System :: POSIX :: Linux
Classifier: Operating System :: MacOS
Requires-Python: >=3.7
License-File: LICENSE
Requires-Dist: numpy
Requires-Dist: matplotlib
Requires-Dist: pyproj
Requires-Dist: colorlog
Requires-Dist: numba
Requires-Dist: cartopy
Requires-Dist: xarray
Requires-Dist: netCDF4
Requires-Dist: scipy
Requires-Dist: rioxarray
Requires-Dist: ls2d
